nbsolutions/__init__.py
nbsolutions/static/main.js
nbsolutions-0.1.1.dist-info/DESCRIPTION.rst
nbsolutions-0.1.1.dist-info/METADATA
nbsolutions-0.1.1.dist-info/RECORD
nbsolutions-0.1.1.dist-info/WHEEL
nbsolutions-0.1.1.dist-info/metadata.json
nbsolutions-0.1.1.dist-info/top_level.txt
