Metadata-Version: 2.0
Name: nbsolutions
Version: 0.1.1
Summary: Simple Jupyter extension that allows the user to mark solution cells
Home-page: https://github.com/jackylu97/nbsolutions
Author: Jacky Lu
Author-email: jackylu97@gmail.com
License: UNKNOWN
Download-URL: https://github.com/jackylu97/nbsolutions/archive/0.1.1.tar.gz
Platform: UNKNOWN
Requires-Dist: notebook
